graphgym/__init__.py
graphgym/checkpoint.py
graphgym/cmd_args.py
graphgym/config.py
graphgym/init.py
graphgym/loader.py
graphgym/loader_pyg.py
graphgym/logger.py
graphgym/loss.py
graphgym/model_builder.py
graphgym/model_builder_pyg.py
graphgym/optimizer.py
graphgym/register.py
graphgym/train.py
graphgym/train_pyg.py
graphgym/contrib/__init__.py
graphgym/contrib/act/__init__.py
graphgym/contrib/act/example.py
graphgym/contrib/config/__init__.py
graphgym/contrib/config/example.py
graphgym/contrib/feature_augment/__init__.py
graphgym/contrib/feature_augment/example.py
graphgym/contrib/feature_encoder/__init__.py
graphgym/contrib/feature_encoder/example.py
graphgym/contrib/head/__init__.py
graphgym/contrib/head/example.py
graphgym/contrib/layer/__init__.py
graphgym/contrib/layer/attconv.py
graphgym/contrib/layer/example.py
graphgym/contrib/layer/generalconv.py
graphgym/contrib/layer/generalconv_ogb.py
graphgym/contrib/layer/generalconv_v2.py
graphgym/contrib/layer/idconv.py
graphgym/contrib/layer/sageinitconv.py
graphgym/contrib/loader/__init__.py
graphgym/contrib/loader/example.py
graphgym/contrib/loss/__init__.py
graphgym/contrib/loss/example.py
graphgym/contrib/network/__init__.py
graphgym/contrib/network/example.py
graphgym/contrib/optimizer/__init__.py
graphgym/contrib/optimizer/example.py
graphgym/contrib/pooling/__init__.py
graphgym/contrib/pooling/example.py
graphgym/contrib/stage/__init__.py
graphgym/contrib/stage/example.py
graphgym/contrib/train/__init__.py
graphgym/contrib/train/example.py
graphgym/contrib/transform/__init__.py
graphgym/contrib/transform/identity.py
graphgym/models/__init__.py
graphgym/models/act.py
graphgym/models/feature_augment.py
graphgym/models/feature_encoder.py
graphgym/models/feature_encoder_pyg.py
graphgym/models/gnn.py
graphgym/models/gnn_pyg.py
graphgym/models/head.py
graphgym/models/head_pyg.py
graphgym/models/layer.py
graphgym/models/layer_pyg.py
graphgym/models/pooling.py
graphgym/models/transform.py
graphgym/utils/__init__.py
graphgym-0.4.0.dist-info/LICENSE
graphgym-0.4.0.dist-info/METADATA
graphgym-0.4.0.dist-info/WHEEL
graphgym-0.4.0.dist-info/top_level.txt
graphgym-0.4.0.dist-info/RECORD
