Metadata-Version: 2.1
Name: graphgym
Version: 0.4.0
Summary: GraphGym: platform for designing and evaluating Graph Neural Networks (GNN)
Home-page: https://github.com/snap-stanford/graphgym
Author: Jiaxuan You
Author-email: jiaxuan@cs.stanford.edu
License: UNKNOWN
Platform: UNKNOWN
Classifier: Programming Language :: Python :: 3
Classifier: License :: OSI Approved :: MIT License
Classifier: Operating System :: OS Independent
Requires-Python: >=3.6
License-File: LICENSE
Requires-Dist: yacs
Requires-Dist: tensorboardx
Requires-Dist: torch
Requires-Dist: torch-geometric
Requires-Dist: networkx
Requires-Dist: numpy
Requires-Dist: deepsnap
Requires-Dist: ogb
